MANIFEST.in
README.md
setup.py
luca/__init__.py
luca/commandline.py
luca/extras.py
luca/files.py
luca/kit.py
luca/ledger.py
luca/model.py
luca/pdf.py
luca/rules.py
luca/tally.py
luca/utils.py
luca.egg-info/PKG-INFO
luca.egg-info/SOURCES.txt
luca.egg-info/dependency_links.txt
luca.egg-info/entry_points.txt
luca.egg-info/requires.txt
luca.egg-info/top_level.txt
luca/forms/__init__.py
luca/forms/actions.py
luca/forms/formlib.py
luca/forms/us/__init__.py
luca/forms/us/f1040.py
luca/forms/us/f1040sa.py
luca/forms/us/f1040sb.py
luca/forms/us/f1040sc.py
luca/forms/us/f1040sd.py
luca/forms/us/f1040se.py
luca/forms/us/f1040sse.py
luca/forms/us/f1099msc.py
luca/forms/us/f1120s.py
luca/forms/us/f1120ssk.py
luca/forms/us/f8829.py
luca/forms/us/f8949.py
luca/forms/us/f940.py
luca/forms/us/f941.py
luca/forms/us/fw9.py
luca/forms/us_ga/__init__.py
luca/forms/us_ga/f600s.py
luca/forms/us_oh/__init__.py
luca/forms/us_oh/it1040.py
luca/forms/us_oh/sd100.py
luca/importer/__init__.py
luca/importer/dccu.py
luca/importer/gnucash.py
luca/importer/model.py
luca/importer/yodlee.py
luca/ofx/__init__.py
luca/ofx/applications.py
luca/ofx/institutions.py
luca/ofx/io.py
luca/ofx/parse.py
luca/ofx/schema.py
luca/ofx/types.py
luca/tests/__init__.py
luca/tests/test_docs.py
luca/tests/test_form.py
luca/tests/test_kit.py
luca/tests/test_ledger.py
luca/tests/test_samples.py