Metadata-Version: 1.1
Name: luca
Version: 1.0
Summary: Do accounting with YAML, fill out tax forms with JSON
Home-page: https://github.com/brandon-rhodes/luca
Author: Brandon Rhodes
Author-email: brandon@rhodesmill.org
License: UNKNOWN
Platform: UNKNOWN
Classifier: Development Status :: 5 - Production/Stable
Classifier: Environment :: Console
Classifier: License :: OSI Approved :: MIT License
Classifier: Programming Language :: Python :: 2.7
Classifier: Topic :: Office/Business
Classifier: Topic :: Office/Business :: Financial
Classifier: Topic :: Office/Business :: Financial :: Accounting
